package1/__init__.py
package1/another_package.py
pacakge1-0.0.1.dist-info/LICENSE
pacakge1-0.0.1.dist-info/METADATA
pacakge1-0.0.1.dist-info/WHEEL
pacakge1-0.0.1.dist-info/top_level.txt
pacakge1-0.0.1.dist-info/RECORD
