Metadata-Version: 2.1
Name: pacakge1
Version: 0.0.1
Summary: A package for importing modules as top-level
Home-page: https://github.com/Shaikh-Ubaid/lpython_packages
Author: Ubaid Shaikh
Author-email: shaikhubaid769@gmail.com
Classifier: Programming Language :: Python :: 3
Classifier: License :: OSI Approved :: MIT License
Classifier: Operating System :: OS Independent
Requires-Python: >=3.6
License-File: LICENSE
